bauhaus_design_kit/__init__.py
bauhaus_design_kit/color_theory.py
bauhaus_design_kit/form_functions.py
bauhaus_design_kit/revit_integration.py
bauhaus_design_kit/spatial_geometry.py
bauhaus_design_kit-0.1.0.dist-info/licenses/LICENSE
bauhaus_design_kit-0.1.0.dist-info/METADATA
bauhaus_design_kit-0.1.0.dist-info/WHEEL
bauhaus_design_kit-0.1.0.dist-info/top_level.txt
bauhaus_design_kit-0.1.0.dist-info/RECORD
