Metadata-Version: 2.4
Name: bauhaus-design-kit
Version: 0.1.0
Summary: Kit de herramientas de diseño inspirado en la Bauhaus
Home-page: https://github.com/Marymvc/PG2_PRACT7.git
Author: Mary Villca
Author-email: marymagalivc@gmail.com
License: MIT
Project-URL: Homepage, https://github.com/Marymvc/PG2_PRACT7.git
Requires-Python: >=3.8
License-File: LICENSE
Dynamic: license-file
